<annotation>
	<folder>train2014</folder>
	<filename>DSC04895.jpg</filename>
	<path>F:\处理病害数据集\images\train2014\DSC04895.jpg</path>
	<source>
		<database>Unknown</database>
	</source>
	<size>
		<width>5472</width>
		<height>3648</height>
		<depth>3</depth>
	</size>
	<segmented>0</segmented>
	<object>
		<name>chihuo_low</name>
		<pose>Unspecified</pose>
		<truncated>0</truncated>
		<difficult>0</difficult>
		<bndbox>
			<xmin>1786</xmin>
			<ymin>995</ymin>
			<xmax>3578</xmax>
			<ymax>2970</ymax>
		</bndbox>
	</object>
	<object>
		<name>tanju_low</name>
		<pose>Unspecified</pose>
		<truncated>0</truncated>
		<difficult>0</difficult>
		<bndbox>
			<xmin>2044</xmin>
			<ymin>3007</ymin>
			<xmax>3678</xmax>
			<ymax>3641</ymax>
		</bndbox>
	</object>
	<object>
		<name>tanju_low</name>
		<pose>Unspecified</pose>
		<truncated>0</truncated>
		<difficult>0</difficult>
		<bndbox>
			<xmin>3657</xmin>
			<ymin>3</ymin>
			<xmax>5461</xmax>
			<ymax>1299</ymax>
		</bndbox>
	</object>
</annotation>
