<annotation>
	<folder>train2014</folder>
	<filename>IMG_4932.jpg</filename>
	<path>F:\处理病害数据集\images\train2014\IMG_4932.jpg</path>
	<source>
		<database>Unknown</database>
	</source>
	<size>
		<width>4032</width>
		<height>3024</height>
		<depth>3</depth>
	</size>
	<segmented>0</segmented>
	<object>
		<name>chihuo_high</name>
		<pose>Unspecified</pose>
		<truncated>0</truncated>
		<difficult>0</difficult>
		<bndbox>
			<xmin>9</xmin>
			<ymin>2030</ymin>
			<xmax>1062</xmax>
			<ymax>2862</ymax>
		</bndbox>
	</object>
	<object>
		<name>healthy</name>
		<pose>Unspecified</pose>
		<truncated>0</truncated>
		<difficult>0</difficult>
		<bndbox>
			<xmin>1316</xmin>
			<ymin>393</ymin>
			<xmax>2469</xmax>
			<ymax>1755</ymax>
		</bndbox>
	</object>
	<object>
		<name>healthy</name>
		<pose>Unspecified</pose>
		<truncated>0</truncated>
		<difficult>0</difficult>
		<bndbox>
			<xmin>2675</xmin>
			<ymin>837</ymin>
			<xmax>3903</xmax>
			<ymax>1465</ymax>
		</bndbox>
	</object>
	<object>
		<name>healthy</name>
		<pose>Unspecified</pose>
		<truncated>0</truncated>
		<difficult>0</difficult>
		<bndbox>
			<xmin>2509</xmin>
			<ymin>2502</ymin>
			<xmax>3731</xmax>
			<ymax>3021</ymax>
		</bndbox>
	</object>
</annotation>
