<annotation>
	<folder>train</folder>
	<filename>IMG_4662.jpg</filename>
	<path>E:\dataset\images\train\IMG_4662.jpg</path>
	<source>
		<database>Unknown</database>
	</source>
	<size>
		<width>4032</width>
		<height>3024</height>
		<depth>3</depth>
	</size>
	<segmented>0</segmented>
	<object>
		<name>healthy</name>
		<pose>Unspecified</pose>
		<truncated>0</truncated>
		<difficult>0</difficult>
		<bndbox>
			<xmin>1097</xmin>
			<ymin>146</ymin>
			<xmax>2003</xmax>
			<ymax>1265</ymax>
		</bndbox>
	</object>
	<object>
		<name>healthy</name>
		<pose>Unspecified</pose>
		<truncated>0</truncated>
		<difficult>0</difficult>
		<bndbox>
			<xmin>2028</xmin>
			<ymin>1377</ymin>
			<xmax>2594</xmax>
			<ymax>1943</ymax>
		</bndbox>
	</object>
	<object>
		<name>chihuo_high</name>
		<pose>Unspecified</pose>
		<truncated>0</truncated>
		<difficult>0</difficult>
		<bndbox>
			<xmin>2087</xmin>
			<ymin>418</ymin>
			<xmax>3941</xmax>
			<ymax>1730</ymax>
		</bndbox>
	</object>
	<object>
		<name>chihuo_high</name>
		<pose>Unspecified</pose>
		<truncated>1</truncated>
		<difficult>0</difficult>
		<bndbox>
			<xmin>1</xmin>
			<ymin>1131</ymin>
			<xmax>1808</xmax>
			<ymax>2150</ymax>
		</bndbox>
	</object>
	<object>
		<name>chihuo_low</name>
		<pose>Unspecified</pose>
		<truncated>0</truncated>
		<difficult>0</difficult>
		<bndbox>
			<xmin>1925</xmin>
			<ymin>2212</ymin>
			<xmax>3131</xmax>
			<ymax>3021</ymax>
		</bndbox>
	</object>
</annotation>
