<annotation>
	<folder>train2014</folder>
	<filename>IMG_3670.jpg</filename>
	<path>F:\处理病害数据集\images\train2014\IMG_3670.jpg</path>
	<source>
		<database>Unknown</database>
	</source>
	<size>
		<width>4032</width>
		<height>3024</height>
		<depth>3</depth>
	</size>
	<segmented>0</segmented>
	<object>
		<name>chihuo_high</name>
		<pose>Unspecified</pose>
		<truncated>0</truncated>
		<difficult>0</difficult>
		<bndbox>
			<xmin>1066</xmin>
			<ymin>562</ymin>
			<xmax>2241</xmax>
			<ymax>1302</ymax>
		</bndbox>
	</object>
	<object>
		<name>chihuo_high</name>
		<pose>Unspecified</pose>
		<truncated>0</truncated>
		<difficult>0</difficult>
		<bndbox>
			<xmin>2375</xmin>
			<ymin>802</ymin>
			<xmax>3484</xmax>
			<ymax>1715</ymax>
		</bndbox>
	</object>
	<object>
		<name>healthy</name>
		<pose>Unspecified</pose>
		<truncated>0</truncated>
		<difficult>0</difficult>
		<bndbox>
			<xmin>2537</xmin>
			<ymin>2</ymin>
			<xmax>3919</xmax>
			<ymax>437</ymax>
		</bndbox>
	</object>
	<object>
		<name>healthy</name>
		<pose>Unspecified</pose>
		<truncated>0</truncated>
		<difficult>0</difficult>
		<bndbox>
			<xmin>2269</xmin>
			<ymin>1540</ymin>
			<xmax>3216</xmax>
			<ymax>2846</ymax>
		</bndbox>
	</object>
	<object>
		<name>healthy</name>
		<pose>Unspecified</pose>
		<truncated>0</truncated>
		<difficult>0</difficult>
		<bndbox>
			<xmin>1387</xmin>
			<ymin>1855</ymin>
			<xmax>2184</xmax>
			<ymax>2621</ymax>
		</bndbox>
	</object>
</annotation>
