<annotation>
	<folder>train2014</folder>
	<filename>IMG_4637.jpg</filename>
	<path>F:\处理病害数据集\images\train2014\IMG_4637.jpg</path>
	<source>
		<database>Unknown</database>
	</source>
	<size>
		<width>4032</width>
		<height>3024</height>
		<depth>3</depth>
	</size>
	<segmented>0</segmented>
	<object>
		<name>healthy</name>
		<pose>Unspecified</pose>
		<truncated>0</truncated>
		<difficult>0</difficult>
		<bndbox>
			<xmin>47</xmin>
			<ymin>1280</ymin>
			<xmax>606</xmax>
			<ymax>1752</ymax>
		</bndbox>
	</object>
	<object>
		<name>healthy</name>
		<pose>Unspecified</pose>
		<truncated>1</truncated>
		<difficult>0</difficult>
		<bndbox>
			<xmin>1</xmin>
			<ymin>1646</ymin>
			<xmax>2181</xmax>
			<ymax>2602</ymax>
		</bndbox>
	</object>
	<object>
		<name>healthy</name>
		<pose>Unspecified</pose>
		<truncated>0</truncated>
		<difficult>0</difficult>
		<bndbox>
			<xmin>2112</xmin>
			<ymin>568</ymin>
			<xmax>2903</xmax>
			<ymax>2005</ymax>
		</bndbox>
	</object>
	<object>
		<name>healthy</name>
		<pose>Unspecified</pose>
		<truncated>0</truncated>
		<difficult>0</difficult>
		<bndbox>
			<xmin>2372</xmin>
			<ymin>252</ymin>
			<xmax>3944</xmax>
			<ymax>2537</ymax>
		</bndbox>
	</object>
</annotation>
