<annotation>
	<folder>train</folder>
	<filename>tea182.jpg</filename>
	<path>E:\dataset\images\train\tea182.jpg</path>
	<source>
		<database>Unknown</database>
	</source>
	<size>
		<width>3840</width>
		<height>3840</height>
		<depth>3</depth>
	</size>
	<segmented>0</segmented>
	<object>
		<name>tanju_high</name>
		<pose>Unspecified</pose>
		<truncated>0</truncated>
		<difficult>0</difficult>
		<bndbox>
			<xmin>12</xmin>
			<ymin>4</ymin>
			<xmax>1036</xmax>
			<ymax>1144</ymax>
		</bndbox>
	</object>
	<object>
		<name>healthy</name>
		<pose>Unspecified</pose>
		<truncated>0</truncated>
		<difficult>0</difficult>
		<bndbox>
			<xmin>1482</xmin>
			<ymin>602</ymin>
			<xmax>2952</xmax>
			<ymax>3686</ymax>
		</bndbox>
	</object>
</annotation>
