<annotation>
	<folder>train</folder>
	<filename>tea156.jpg</filename>
	<path>E:\dataset\images\train\tea156.jpg</path>
	<source>
		<database>Unknown</database>
	</source>
	<size>
		<width>5920</width>
		<height>2664</height>
		<depth>3</depth>
	</size>
	<segmented>0</segmented>
	<object>
		<name>chihuo_high</name>
		<pose>Unspecified</pose>
		<truncated>0</truncated>
		<difficult>0</difficult>
		<bndbox>
			<xmin>1187</xmin>
			<ymin>118</ymin>
			<xmax>2755</xmax>
			<ymax>2654</ymax>
		</bndbox>
	</object>
	<object>
		<name>chihuo_low</name>
		<pose>Unspecified</pose>
		<truncated>0</truncated>
		<difficult>0</difficult>
		<bndbox>
			<xmin>2701</xmin>
			<ymin>9</ymin>
			<xmax>4728</xmax>
			<ymax>2291</ymax>
		</bndbox>
	</object>
	<object>
		<name>chihuo_high</name>
		<pose>Unspecified</pose>
		<truncated>0</truncated>
		<difficult>0</difficult>
		<bndbox>
			<xmin>554</xmin>
			<ymin>857</ymin>
			<xmax>1529</xmax>
			<ymax>1745</ymax>
		</bndbox>
	</object>
</annotation>
